Metadata-Version: 2.1
Name: gsocket
Version: 0.0.1
Summary: 一个 socket 模块
Home-page: https://github.com/Leviathangk/gsocket
Author: 郭一会儿
Author-email: 1015295213@qq.com
License: MIT Licence
Keywords: socket
Platform: any
